setup.py
curl_http/__init__.py
curl_http/curl_http.py
curl_http/test.py
curl_http.egg-info/PKG-INFO
curl_http.egg-info/SOURCES.txt
curl_http.egg-info/dependency_links.txt
curl_http.egg-info/requires.txt
curl_http.egg-info/top_level.txt