Metadata-Version: 1.0
Name: curl_http
Version: 0.1.2
Summary: curl_http is a wrapper for PyCUrl
Home-page: https://github.com/LDouble/curl_http
Author: DoubleL
Author-email: 2943200389@qq.com
License: MIT Licence
Keywords: curl,http,HTTP,curl_http,PyCUrl
Platform: any
